neuralGAM/__init__.py
neuralGAM/dataset.py
neuralGAM/metrics.py
neuralGAM/model.py
neuralGAM/neuralGAM.py
neuralGAM/plot.py
neuralgam-1.0.1.dist-info/licenses/LICENSE
neuralgam-1.0.1.dist-info/METADATA
neuralgam-1.0.1.dist-info/WHEEL
neuralgam-1.0.1.dist-info/top_level.txt
neuralgam-1.0.1.dist-info/RECORD
