Metadata-Version: 2.4
Name: neuralGAM
Version: 1.0.1
Summary: Neural network framework based on Generalized Additive Models.
Home-page: https://github.com/inesortega/pyNeuralGAM
Author: Ines Ortega-Fernandez, Marta Sestelo
Author-email: Ines Ortega-Fernandez <iortega@gradiant.org>, Marta Sestelo <sestelo@uvigo.gal>
Maintainer-email: Ines Ortega-Fernandez <iortega@gradiant.org>
License: Mozilla Public License Version 2.0
Project-URL: Repository, https://github.com/inesortega/pyneuralGAM
Project-URL: Issues, https://github.com/inesortega/pyNeuralGAM/issues
Project-URL: Homepage, https://inesortega.github.io/software/2023-neuralGAM
Keywords: deep neural networks,explainable ai,xAI,Generalized Additive Models
Classifier: Programming Language :: Python :: 3
Classifier: Operating System :: OS Independent
Requires-Python: >=3.9
License-File: LICENSE
Requires-Dist: tensorflow[and-cuda]==2.12.0
Requires-Dist: argparse
Requires-Dist: matplotlib==3.9.4
Requires-Dist: scikit-learn==1.3.0
Requires-Dist: seaborn==0.13.2
Requires-Dist: scipy==1.13.1
Requires-Dist: keras
Requires-Dist: numpy
Requires-Dist: pandas
Requires-Dist: dill==0.3.6
Requires-Dist: joblib==1.3.2
Dynamic: author
Dynamic: home-page
Dynamic: license-file
